ipv4ac/__about__.py
ipv4ac/__init__.py
ipv4ac/ipv4ac.py
ipv4ac-1.0.0b0.dist-info/METADATA
ipv4ac-1.0.0b0.dist-info/WHEEL
ipv4ac-1.0.0b0.dist-info/licenses/LICENSE
ipv4ac-1.0.0b0.dist-info/RECORD
