Metadata-Version: 2.1
Name: ipv4ac
Version: 1.0.0b0
Summary: A simple module provides a function to check if an IPv4 address has correct format.
Project-URL: Repository, https://github.com/drazkgi/ipv4ac
Author-email: Bartłomiej Drążkiewicz <bartlomiej@drazkiewicz.me>
License-Expression: MIT
License-File: LICENSE
Keywords: check,ip,ipv4,mit,module,network,pattern,python
Classifier: Development Status :: 4 - Beta
Classifier: License :: OSI Approved :: MIT License
Classifier: Operating System :: OS Independent
Classifier: Programming Language :: Python :: 3
Classifier: Topic :: Software Development :: Libraries :: Python Modules
Classifier: Topic :: System :: Networking
Requires-Python: >=3.8
